http_prompt/__init__.py
http_prompt/cli.py
http_prompt/completer.py
http_prompt/completion.py
http_prompt/config.py
http_prompt/contextio.py
http_prompt/defaultconfig.py
http_prompt/execution.py
http_prompt/lexer.py
http_prompt/options.py
http_prompt/output.py
http_prompt/tree.py
http_prompt/utils.py
http_prompt/xdg.py
http_prompt/context/__init__.py
http_prompt/context/transform.py
http_prompt-2.1.0.dist-info/LICENSE
http_prompt-2.1.0.dist-info/METADATA
http_prompt-2.1.0.dist-info/WHEEL
http_prompt-2.1.0.dist-info/entry_points.txt
http_prompt-2.1.0.dist-info/top_level.txt
http_prompt-2.1.0.dist-info/RECORD
