Metadata-Version: 2.1
Name: http-prompt
Version: 2.1.0
Summary: An interactive HTTP command-line client
Home-page: https://github.com/httpie/http-prompt
Author: Chang-Hung Liang
Author-email: eliang.cs@gmail.com
License: MIT
Platform: UNKNOWN
Classifier: Development Status :: 3 - Alpha
Classifier: Environment :: Console
Classifier: Intended Audience :: Developers
Classifier: Intended Audience :: System Administrators
Classifier: License :: OSI Approved :: MIT License
Classifier: Topic :: Internet :: WWW/HTTP
Classifier: Topic :: Software Development
Classifier: Topic :: System :: Networking
Classifier: Topic :: Terminals
Classifier: Topic :: Text Processing
Classifier: Topic :: Utilities
Classifier: Operating System :: OS Independent
Classifier: Programming Language :: Python
Classifier: Programming Language :: Python :: 3.6
Classifier: Programming Language :: Python :: 3.7
Classifier: Programming Language :: Python :: 3.8
Classifier: Programming Language :: Python :: 3.9
Requires-Dist: click (>=5.0)
Requires-Dist: httpie (>=2.4.0)
Requires-Dist: parsimonious (>=0.6.2)
Requires-Dist: prompt-toolkit (<2.0.0,>=1.0.0)
Requires-Dist: Pygments (>=2.1.0)
Requires-Dist: PyYAML (>=3.0)
